LICENSE.txt
MANIFEST.in
NEWS.rst
README.rst
setup.py
src/blacktie/__init__.py
src/blacktie.egg-info/PKG-INFO
src/blacktie.egg-info/SOURCES.txt
src/blacktie.egg-info/dependency_links.txt
src/blacktie.egg-info/entry_points.txt
src/blacktie.egg-info/not-zip-safe
src/blacktie.egg-info/requires.txt
src/blacktie.egg-info/top_level.txt
src/blacktie/scripts/__init__.py
src/blacktie/scripts/blacktie_pipeline.py
src/blacktie/scripts/cummerbund.py
src/blacktie/scripts/encode_mail_li_file.py
src/blacktie/utils/__init__.py
src/blacktie/utils/calls.py
src/blacktie/utils/errors.py
src/blacktie/utils/externals.py
src/blacktie/utils/misc.py