Metadata-Version: 1.0
Name: blacktie
Version: 0.2.1.2
Summary: A python wrapper for analysis of RNA-seq data with the popular tophat/cufflinks pipeline.
Home-page: https://github.com/xguse/
Author: Augustine Dunn
Author-email: wadunn83@gmail.com
License: GPL 3
Keywords: scientific computing RNA-seq tophat cufflinks bowtie CummeRbund
Platform: UNKNOWN
